{
  "properties": {
    "activities": [
      {
        "type": "Copy",
        "typeProperties": {
          "source": {
            "type": "BinarySource",
            "formatSettings": {
              "type": "BinaryReadSettings"
            },
            "storeSettings": {
              "type": "AzureBlobStorageReadSettings",
              "recursive": true
            },
            "datasetSettings": {
              "type": "Binary",
              "typeProperties": {
                "location": {
                  "type": "AzureBlobStorageLocation",
                  "container": "fabrictrainingdata",
                  "fileName": "order_products__prior.csv"
                }
              },
              "externalReferences": {
                "connection": "dc4de05f-3dd3-4b8e-b067-7000252a438f"
              },
              "annotations": []
            }
          },
          "sink": {
            "type": "BinarySink",
            "storeSettings": {
              "type": "LakehouseWriteSettings"
            },
            "datasetSettings": {
              "type": "Binary",
              "typeProperties": {
                "location": {
                  "type": "LakehouseLocation",
                  "fileName": "order.csv"
                }
              },
              "linkedService": {
                "name": "CrossTenantADLS",
                "properties": {
                  "type": "Lakehouse",
                  "typeProperties": {
                    "artifactId": "0eb83d66-9f1c-a120-4606-bb274bcc1f30",
                    "workspaceId": "00000000-0000-0000-0000-000000000000",
                    "rootFolder": "Files"
                  },
                  "annotations": []
                }
              },
              "annotations": []
            }
          },
          "enableStaging": false
        },
        "policy": {
          "timeout": "0.12:00:00",
          "retry": 0,
          "retryIntervalInSeconds": 30,
          "secureInput": false,
          "secureOutput": false
        },
        "name": "Copy data1",
        "dependsOn": []
      }
    ]
  }
}